gptneox20b/__init__.py
gptneox20b/cli.py
gptneox20b/run_isolated.py
gptneox20b/assets/example.txt
gptneox20b-1.0.3.dist-info/LICENSE
gptneox20b-1.0.3.dist-info/METADATA
gptneox20b-1.0.3.dist-info/WHEEL
gptneox20b-1.0.3.dist-info/entry_points.txt
gptneox20b-1.0.3.dist-info/top_level.txt
gptneox20b-1.0.3.dist-info/RECORD
