Metadata-Version: 2.1
Name: gptneox20b
Version: 1.0.3
Summary: test for a gpt model
Home-page: https://github.com/zackees/gptneox20b
Maintainer: Zachary Vorhies
License: BSD 3-Clause License
Keywords: template-python-cmd
Classifier: Programming Language :: Python :: 3
Requires-Python: >=3.7
License-File: LICENSE
Requires-Dist: isolated-environment
Requires-Dist: transformers
Requires-Dist: sentencepiece
Requires-Dist: accelerate
Requires-Dist: safetensors
